base32hex.py
setup.cfg
setup.py
xid.py
xid.egg-info/PKG-INFO
xid.egg-info/SOURCES.txt
xid.egg-info/dependency_links.txt
xid.egg-info/top_level.txt