Metadata-Version: 1.1
Name: xid
Version: 1.0.4
Summary: Python Xid Implementation
Home-page: https://github.com/graham/python_xid
Author: Graham Abbott
Author-email: graham.abbott@gmail.com
License: MIT
Download-URL: https://github.com/graham/python_xid/tarball/0.1
Platform: UNKNOWN
